{
  "Maize": [
    [
      {
        "y": 15215000.0, 
        "x": 1961
      }, 
      {
        "y": 12818000.0, 
        "x": 1962
      }, 
      {
        "y": 15379210.0, 
        "x": 1963
      }, 
      {
        "y": 15368015.0, 
        "x": 1964
      }, 
      {
        "y": 15673615.0, 
        "x": 1965
      }, 
      {
        "y": 17024011.0, 
        "x": 1966
      }, 
      {
        "y": 16021386.0, 
        "x": 1967
      }, 
      {
        "y": 16022641.0, 
        "x": 1968
      }, 
      {
        "y": 16019040.0, 
        "x": 1969
      }, 
      {
        "y": 15838000.0, 
        "x": 1970
      }, 
      {
        "y": 16731276.0, 
        "x": 1971
      }, 
      {
        "y": 16711746.0, 
        "x": 1972
      }, 
      {
        "y": 16584528.0, 
        "x": 1973
      }, 
      {
        "y": 17431829.0, 
        "x": 1974
      }, 
      {
        "y": 18628717.0, 
        "x": 1975
      }, 
      {
        "y": 19250413.0, 
        "x": 1976
      }, 
      {
        "y": 19674052.0, 
        "x": 1977
      }, 
      {
        "y": 19997972.0, 
        "x": 1978
      }, 
      {
        "y": 20146329.0, 
        "x": 1979
      }, 
      {
        "y": 20372005.0, 
        "x": 1980
      }, 
      {
        "y": 19440250.0, 
        "x": 1981
      }, 
      {
        "y": 18564110.0, 
        "x": 1982
      }, 
      {
        "y": 18867732.0, 
        "x": 1983
      }, 
      {
        "y": 18589193.0, 
        "x": 1984
      }, 
      {
        "y": 17755636.0, 
        "x": 1985
      }, 
      {
        "y": 19198886.0, 
        "x": 1986
      }, 
      {
        "y": 20290839.0, 
        "x": 1987
      }, 
      {
        "y": 19773883.0, 
        "x": 1988
      }, 
      {
        "y": 20433863.0, 
        "x": 1989
      }, 
      {
        "y": 21482669.0, 
        "x": 1990
      }, 
      {
        "y": 21648560.0, 
        "x": 1991
      }, 
      {
        "y": 21119959.0, 
        "x": 1992
      }, 
      {
        "y": 20770836.0, 
        "x": 1993
      }, 
      {
        "y": 21229239.0, 
        "x": 1994
      }, 
      {
        "y": 22848767.0, 
        "x": 1995
      }, 
      {
        "y": 24571077.0, 
        "x": 1996
      }, 
      {
        "y": 23836847.0, 
        "x": 1997
      }, 
      {
        "y": 25281364.0, 
        "x": 1998
      }, 
      {
        "y": 25938854.0, 
        "x": 1999
      }, 
      {
        "y": 23086418.0, 
        "x": 2000
      }, 
      {
        "y": 24310656.0, 
        "x": 2001
      }, 
      {
        "y": 24661127.0, 
        "x": 2002
      }, 
      {
        "y": 24092660.0, 
        "x": 2003
      }, 
      {
        "y": 25467475.0, 
        "x": 2004
      }, 
      {
        "y": 26379250.0, 
        "x": 2005
      }, 
      {
        "y": 26990569.0, 
        "x": 2006
      }, 
      {
        "y": 29497391.0, 
        "x": 2007
      }, 
      {
        "y": 29882698.0, 
        "x": 2008
      }, 
      {
        "y": 31203727.0, 
        "x": 2009
      }, 
      {
        "y": 32517868.0, 
        "x": 2010
      }, 
      {
        "y": 33560700.0, 
        "x": 2011
      }
    ]
  ], 
  "Wheat": [
    [
      {
        "y": 25567759.0, 
        "x": 1961
      }, 
      {
        "y": 24071363.0, 
        "x": 1962
      }, 
      {
        "y": 23764512.0, 
        "x": 1963
      }, 
      {
        "y": 25391511.0, 
        "x": 1964
      }, 
      {
        "y": 24696119.0, 
        "x": 1965
      }, 
      {
        "y": 23908507.0, 
        "x": 1966
      }, 
      {
        "y": 25285891.0, 
        "x": 1967
      }, 
      {
        "y": 24640716.0, 
        "x": 1968
      }, 
      {
        "y": 25141660.0, 
        "x": 1969
      }, 
      {
        "y": 25435003.0, 
        "x": 1970
      }, 
      {
        "y": 25615036.0, 
        "x": 1971
      }, 
      {
        "y": 26276672.0, 
        "x": 1972
      }, 
      {
        "y": 26412386.0, 
        "x": 1973
      }, 
      {
        "y": 27034304.0, 
        "x": 1974
      }, 
      {
        "y": 27634268.0, 
        "x": 1975
      }, 
      {
        "y": 28380502.0, 
        "x": 1976
      }, 
      {
        "y": 28037558.0, 
        "x": 1977
      }, 
      {
        "y": 29184151.0, 
        "x": 1978
      }, 
      {
        "y": 29320977.0, 
        "x": 1979
      }, 
      {
        "y": 29191137.0, 
        "x": 1980
      }, 
      {
        "y": 28279019.0, 
        "x": 1981
      }, 
      {
        "y": 27928008.0, 
        "x": 1982
      }, 
      {
        "y": 29051138.0, 
        "x": 1983
      }, 
      {
        "y": 29577517.0, 
        "x": 1984
      }, 
      {
        "y": 29219053.0, 
        "x": 1985
      }, 
      {
        "y": 29617134.0, 
        "x": 1986
      }, 
      {
        "y": 28799188.0, 
        "x": 1987
      }, 
      {
        "y": 28785660.0, 
        "x": 1988
      }, 
      {
        "y": 29842159.0, 
        "x": 1989
      }, 
      {
        "y": 30754285.0, 
        "x": 1990
      }, 
      {
        "y": 30949090.0, 
        "x": 1991
      }, 
      {
        "y": 30497202.0, 
        "x": 1992
      }, 
      {
        "y": 30236410.0, 
        "x": 1993
      }, 
      {
        "y": 28981966.0, 
        "x": 1994
      }, 
      {
        "y": 28861315.0, 
        "x": 1995
      }, 
      {
        "y": 29611057.0, 
        "x": 1996
      }, 
      {
        "y": 30057020.0, 
        "x": 1997
      }, 
      {
        "y": 29775127.0, 
        "x": 1998
      }, 
      {
        "y": 28855019.0, 
        "x": 1999
      }, 
      {
        "y": 26653336.0, 
        "x": 2000
      }, 
      {
        "y": 24664068.0, 
        "x": 2001
      }, 
      {
        "y": 23908072.0, 
        "x": 2002
      }, 
      {
        "y": 21997075.0, 
        "x": 2003
      }, 
      {
        "y": 21626074.0, 
        "x": 2004
      }, 
      {
        "y": 22792462.0, 
        "x": 2005
      }, 
      {
        "y": 22961567.0, 
        "x": 2006
      }, 
      {
        "y": 23721070.0, 
        "x": 2007
      }, 
      {
        "y": 23617266.0, 
        "x": 2008
      }, 
      {
        "y": 24291081.0, 
        "x": 2009
      }, 
      {
        "y": 24256086.0, 
        "x": 2010
      }, 
      {
        "y": 24270480.0, 
        "x": 2011
      }
    ]
  ], 
  "Soybeans": [
    [
      {
        "y": 10006582.0, 
        "x": 1961
      }, 
      {
        "y": 9548938.0, 
        "x": 1962
      }, 
      {
        "y": 9678923.0, 
        "x": 1963
      }, 
      {
        "y": 10049620.0, 
        "x": 1964
      }, 
      {
        "y": 8637176.0, 
        "x": 1965
      }, 
      {
        "y": 8468326.0, 
        "x": 1966
      }, 
      {
        "y": 8546302.0, 
        "x": 1967
      }, 
      {
        "y": 8403461.0, 
        "x": 1968
      }, 
      {
        "y": 8365277.0, 
        "x": 1969
      }, 
      {
        "y": 8019749.0, 
        "x": 1970
      }, 
      {
        "y": 7824151.0, 
        "x": 1971
      }, 
      {
        "y": 7612123.0, 
        "x": 1972
      }, 
      {
        "y": 7436491.0, 
        "x": 1973
      }, 
      {
        "y": 7298454.0, 
        "x": 1974
      }, 
      {
        "y": 7033446.0, 
        "x": 1975
      }, 
      {
        "y": 6719549.0, 
        "x": 1976
      }, 
      {
        "y": 6868117.0, 
        "x": 1977
      }, 
      {
        "y": 7168473.0, 
        "x": 1978
      }, 
      {
        "y": 7258333.0, 
        "x": 1979
      }, 
      {
        "y": 7234329.0, 
        "x": 1980
      }, 
      {
        "y": 8025312.0, 
        "x": 1981
      }, 
      {
        "y": 8417782.0, 
        "x": 1982
      }, 
      {
        "y": 7565192.0, 
        "x": 1983
      }, 
      {
        "y": 7291535.0, 
        "x": 1984
      }, 
      {
        "y": 7725111.0, 
        "x": 1985
      }, 
      {
        "y": 8305277.0, 
        "x": 1986
      }, 
      {
        "y": 8453942.0, 
        "x": 1987
      }, 
      {
        "y": 8127699.0, 
        "x": 1988
      }, 
      {
        "y": 8063021.0, 
        "x": 1989
      }, 
      {
        "y": 7563788.0, 
        "x": 1990
      }, 
      {
        "y": 7045042.0, 
        "x": 1991
      }, 
      {
        "y": 7224940.0, 
        "x": 1992
      }, 
      {
        "y": 9459499.0, 
        "x": 1993
      }, 
      {
        "y": 9227491.0, 
        "x": 1994
      }, 
      {
        "y": 8130844.0, 
        "x": 1995
      }, 
      {
        "y": 7475774.0, 
        "x": 1996
      }, 
      {
        "y": 8347983.0, 
        "x": 1997
      }, 
      {
        "y": 8500855.0, 
        "x": 1998
      }, 
      {
        "y": 7962163.0, 
        "x": 1999
      }, 
      {
        "y": 9306913.0, 
        "x": 2000
      }, 
      {
        "y": 9481968.0, 
        "x": 2001
      }, 
      {
        "y": 8721629.0, 
        "x": 2002
      }, 
      {
        "y": 9312715.0, 
        "x": 2003
      }, 
      {
        "y": 9581835.0, 
        "x": 2004
      }, 
      {
        "y": 9593710.0, 
        "x": 2005
      }, 
      {
        "y": 9304485.0, 
        "x": 2006
      }, 
      {
        "y": 8753868.0, 
        "x": 2007
      }, 
      {
        "y": 9127174.0, 
        "x": 2008
      }, 
      {
        "y": 9190123.0, 
        "x": 2009
      }, 
      {
        "y": 8516115.0, 
        "x": 2010
      }, 
      {
        "y": 7650057.0, 
        "x": 2011
      }
    ]
  ], 
  "Groundnuts, with shell": [
    [
      {
        "y": 1297350.0, 
        "x": 1961
      }, 
      {
        "y": 1396250.0, 
        "x": 1962
      }, 
      {
        "y": 1552542.0, 
        "x": 1963
      }, 
      {
        "y": 1900775.0, 
        "x": 1964
      }, 
      {
        "y": 1949321.0, 
        "x": 1965
      }, 
      {
        "y": 2013026.0, 
        "x": 1966
      }, 
      {
        "y": 2027906.0, 
        "x": 1967
      }, 
      {
        "y": 1834317.0, 
        "x": 1968
      }, 
      {
        "y": 1825385.0, 
        "x": 1969
      }, 
      {
        "y": 1795477.0, 
        "x": 1970
      }, 
      {
        "y": 1871400.0, 
        "x": 1971
      }, 
      {
        "y": 1952250.0, 
        "x": 1972
      }, 
      {
        "y": 1832079.0, 
        "x": 1973
      }, 
      {
        "y": 1889414.0, 
        "x": 1974
      }, 
      {
        "y": 1939100.0, 
        "x": 1975
      }, 
      {
        "y": 1897807.0, 
        "x": 1976
      }, 
      {
        "y": 1738413.0, 
        "x": 1977
      }, 
      {
        "y": 1823673.0, 
        "x": 1978
      }, 
      {
        "y": 2126520.0, 
        "x": 1979
      }, 
      {
        "y": 2389974.0, 
        "x": 1980
      }, 
      {
        "y": 2520853.0, 
        "x": 1981
      }, 
      {
        "y": 2464645.0, 
        "x": 1982
      }, 
      {
        "y": 2244668.0, 
        "x": 1983
      }, 
      {
        "y": 2470705.0, 
        "x": 1984
      }, 
      {
        "y": 3370935.0, 
        "x": 1985
      }, 
      {
        "y": 3302164.0, 
        "x": 1986
      }, 
      {
        "y": 3086489.0, 
        "x": 1987
      }, 
      {
        "y": 3022638.0, 
        "x": 1988
      }, 
      {
        "y": 2980267.0, 
        "x": 1989
      }, 
      {
        "y": 2941453.0, 
        "x": 1990
      }, 
      {
        "y": 2919889.0, 
        "x": 1991
      }, 
      {
        "y": 3012861.0, 
        "x": 1992
      }, 
      {
        "y": 3411035.0, 
        "x": 1993
      }, 
      {
        "y": 3810900.0, 
        "x": 1994
      }, 
      {
        "y": 3848164.0, 
        "x": 1995
      }, 
      {
        "y": 3649504.0, 
        "x": 1996
      }, 
      {
        "y": 3755300.0, 
        "x": 1997
      }, 
      {
        "y": 4069900.0, 
        "x": 1998
      }, 
      {
        "y": 4294500.0, 
        "x": 1999
      }, 
      {
        "y": 4884910.0, 
        "x": 2000
      }, 
      {
        "y": 5016421.0, 
        "x": 2001
      }, 
      {
        "y": 4946100.0, 
        "x": 2002
      }, 
      {
        "y": 5082000.0, 
        "x": 2003
      }, 
      {
        "y": 4766685.0, 
        "x": 2004
      }, 
      {
        "y": 4684628.0, 
        "x": 2005
      }, 
      {
        "y": 3980323.0, 
        "x": 2006
      }, 
      {
        "y": 3967969.0, 
        "x": 2007
      }, 
      {
        "y": 4268322.0, 
        "x": 2008
      }, 
      {
        "y": 4398431.0, 
        "x": 2009
      }, 
      {
        "y": 4547917.0, 
        "x": 2010
      }, 
      {
        "y": 4673400.0, 
        "x": 2011
      }
    ]
  ], 
  "Seed cotton": [
    [
      {
        "y": 3868102.0, 
        "x": 1961
      }, 
      {
        "y": 3496515.0, 
        "x": 1962
      }, 
      {
        "y": 4407351.0, 
        "x": 1963
      }, 
      {
        "y": 4932595.0, 
        "x": 1964
      }, 
      {
        "y": 5000085.0, 
        "x": 1965
      }, 
      {
        "y": 4921543.0, 
        "x": 1966
      }, 
      {
        "y": 5094552.0, 
        "x": 1967
      }, 
      {
        "y": 4982590.0, 
        "x": 1968
      }, 
      {
        "y": 4826761.0, 
        "x": 1969
      }, 
      {
        "y": 4993921.0, 
        "x": 1970
      }, 
      {
        "y": 4919424.0, 
        "x": 1971
      }, 
      {
        "y": 4892173.0, 
        "x": 1972
      }, 
      {
        "y": 4938046.0, 
        "x": 1973
      }, 
      {
        "y": 5008785.0, 
        "x": 1974
      }, 
      {
        "y": 4950338.0, 
        "x": 1975
      }, 
      {
        "y": 4924196.0, 
        "x": 1976
      }, 
      {
        "y": 4840219.0, 
        "x": 1977
      }, 
      {
        "y": 4862253.0, 
        "x": 1978
      }, 
      {
        "y": 4507173.0, 
        "x": 1979
      }, 
      {
        "y": 4915209.0, 
        "x": 1980
      }, 
      {
        "y": 5180135.0, 
        "x": 1981
      }, 
      {
        "y": 5823100.0, 
        "x": 1982
      }, 
      {
        "y": 6071205.0, 
        "x": 1983
      }, 
      {
        "y": 6916003.0, 
        "x": 1984
      }, 
      {
        "y": 5140072.0, 
        "x": 1985
      }, 
      {
        "y": 4306076.0, 
        "x": 1986
      }, 
      {
        "y": 4844020.0, 
        "x": 1987
      }, 
      {
        "y": 5529042.0, 
        "x": 1988
      }, 
      {
        "y": 5203306.0, 
        "x": 1989
      }, 
      {
        "y": 5588105.0, 
        "x": 1990
      }, 
      {
        "y": 6538474.0, 
        "x": 1991
      }, 
      {
        "y": 6835001.0, 
        "x": 1992
      }, 
      {
        "y": 4985001.0, 
        "x": 1993
      }, 
      {
        "y": 5528001.0, 
        "x": 1994
      }, 
      {
        "y": 5422000.0, 
        "x": 1995
      }, 
      {
        "y": 4722290.0, 
        "x": 1996
      }, 
      {
        "y": 4491000.0, 
        "x": 1997
      }, 
      {
        "y": 4459210.0, 
        "x": 1998
      }, 
      {
        "y": 3725600.0, 
        "x": 1999
      }, 
      {
        "y": 4041000.0, 
        "x": 2000
      }, 
      {
        "y": 4809740.0, 
        "x": 2001
      }, 
      {
        "y": 4184200.0, 
        "x": 2002
      }, 
      {
        "y": 5111000.0, 
        "x": 2003
      }, 
      {
        "y": 5693000.0, 
        "x": 2004
      }, 
      {
        "y": 5061900.0, 
        "x": 2005
      }, 
      {
        "y": 5815700.0, 
        "x": 2006
      }, 
      {
        "y": 5926100.0, 
        "x": 2007
      }, 
      {
        "y": 5754100.0, 
        "x": 2008
      }, 
      {
        "y": 4951830.0, 
        "x": 2009
      }, 
      {
        "y": 4849000.0, 
        "x": 2010
      }, 
      {
        "y": 5037000.0, 
        "x": 2011
      }
    ]
  ], 
  "Sweet potatoes": [
    [
      {
        "y": 10853700.0, 
        "x": 1961
      }, 
      {
        "y": 10894600.0, 
        "x": 1962
      }, 
      {
        "y": 9268800.0, 
        "x": 1963
      }, 
      {
        "y": 9893902.0, 
        "x": 1964
      }, 
      {
        "y": 9242560.0, 
        "x": 1965
      }, 
      {
        "y": 9872044.0, 
        "x": 1966
      }, 
      {
        "y": 8942930.0, 
        "x": 1967
      }, 
      {
        "y": 8538516.0, 
        "x": 1968
      }, 
      {
        "y": 8769726.0, 
        "x": 1969
      }, 
      {
        "y": 8935963.0, 
        "x": 1970
      }, 
      {
        "y": 8519493.0, 
        "x": 1971
      }, 
      {
        "y": 9240784.0, 
        "x": 1972
      }, 
      {
        "y": 9495911.0, 
        "x": 1973
      }, 
      {
        "y": 9238452.0, 
        "x": 1974
      }, 
      {
        "y": 9014955.0, 
        "x": 1975
      }, 
      {
        "y": 8478835.0, 
        "x": 1976
      }, 
      {
        "y": 9309140.0, 
        "x": 1977
      }, 
      {
        "y": 9635725.0, 
        "x": 1978
      }, 
      {
        "y": 8715360.0, 
        "x": 1979
      }, 
      {
        "y": 7905315.0, 
        "x": 1980
      }, 
      {
        "y": 7264502.0, 
        "x": 1981
      }, 
      {
        "y": 7045558.0, 
        "x": 1982
      }, 
      {
        "y": 6986150.0, 
        "x": 1983
      }, 
      {
        "y": 6597841.0, 
        "x": 1984
      }, 
      {
        "y": 6117283.0, 
        "x": 1985
      }, 
      {
        "y": 6206096.0, 
        "x": 1986
      }, 
      {
        "y": 6299767.0, 
        "x": 1987
      }, 
      {
        "y": 6321377.0, 
        "x": 1988
      }, 
      {
        "y": 6286324.0, 
        "x": 1989
      }, 
      {
        "y": 6304767.0, 
        "x": 1990
      }, 
      {
        "y": 6212229.0, 
        "x": 1991
      }, 
      {
        "y": 6261973.0, 
        "x": 1992
      }, 
      {
        "y": 6230993.0, 
        "x": 1993
      }, 
      {
        "y": 6072745.0, 
        "x": 1994
      }, 
      {
        "y": 6095642.0, 
        "x": 1995
      }, 
      {
        "y": 6070696.0, 
        "x": 1996
      }, 
      {
        "y": 5973592.0, 
        "x": 1997
      }, 
      {
        "y": 5948853.0, 
        "x": 1998
      }, 
      {
        "y": 5945975.0, 
        "x": 1999
      }, 
      {
        "y": 5824370.0, 
        "x": 2000
      }, 
      {
        "y": 5507259.0, 
        "x": 2001
      }, 
      {
        "y": 5223027.0, 
        "x": 2002
      }, 
      {
        "y": 5189009.0, 
        "x": 2003
      }, 
      {
        "y": 4868286.0, 
        "x": 2004
      }, 
      {
        "y": 4632338.0, 
        "x": 2005
      }, 
      {
        "y": 3673620.0, 
        "x": 2006
      }, 
      {
        "y": 3661434.0, 
        "x": 2007
      }, 
      {
        "y": 3773657.0, 
        "x": 2008
      }, 
      {
        "y": 3560696.0, 
        "x": 2009
      }, 
      {
        "y": 3554271.0, 
        "x": 2010
      }, 
      {
        "y": 3490925.0, 
        "x": 2011
      }
    ]
  ], 
  "Rapeseed": [
    [
      {
        "y": 1473918.0, 
        "x": 1961
      }, 
      {
        "y": 1369345.0, 
        "x": 1962
      }, 
      {
        "y": 1452398.0, 
        "x": 1963
      }, 
      {
        "y": 1807598.0, 
        "x": 1964
      }, 
      {
        "y": 1841693.0, 
        "x": 1965
      }, 
      {
        "y": 1753679.0, 
        "x": 1966
      }, 
      {
        "y": 1667498.0, 
        "x": 1967
      }, 
      {
        "y": 1405888.0, 
        "x": 1968
      }, 
      {
        "y": 1428221.0, 
        "x": 1969
      }, 
      {
        "y": 1453722.0, 
        "x": 1970
      }, 
      {
        "y": 1615535.0, 
        "x": 1971
      }, 
      {
        "y": 1966471.0, 
        "x": 1972
      }, 
      {
        "y": 2095298.0, 
        "x": 1973
      }, 
      {
        "y": 2062083.0, 
        "x": 1974
      }, 
      {
        "y": 2314364.0, 
        "x": 1975
      }, 
      {
        "y": 2348311.0, 
        "x": 1976
      }, 
      {
        "y": 2218045.0, 
        "x": 1977
      }, 
      {
        "y": 2599967.0, 
        "x": 1978
      }, 
      {
        "y": 2760382.0, 
        "x": 1979
      }, 
      {
        "y": 2842973.0, 
        "x": 1980
      }, 
      {
        "y": 3798476.0, 
        "x": 1981
      }, 
      {
        "y": 4119326.0, 
        "x": 1982
      }, 
      {
        "y": 3666679.0, 
        "x": 1983
      }, 
      {
        "y": 3413617.0, 
        "x": 1984
      }, 
      {
        "y": 4494485.0, 
        "x": 1985
      }, 
      {
        "y": 4916540.0, 
        "x": 1986
      }, 
      {
        "y": 5267609.0, 
        "x": 1987
      }, 
      {
        "y": 4936110.0, 
        "x": 1988
      }, 
      {
        "y": 4992754.0, 
        "x": 1989
      }, 
      {
        "y": 5503534.0, 
        "x": 1990
      }, 
      {
        "y": 6133178.0, 
        "x": 1991
      }, 
      {
        "y": 5975847.0, 
        "x": 1992
      }, 
      {
        "y": 5300103.0, 
        "x": 1993
      }, 
      {
        "y": 5783136.0, 
        "x": 1994
      }, 
      {
        "y": 6907012.0, 
        "x": 1995
      }, 
      {
        "y": 6733760.0, 
        "x": 1996
      }, 
      {
        "y": 6475006.0, 
        "x": 1997
      }, 
      {
        "y": 6527047.0, 
        "x": 1998
      }, 
      {
        "y": 6899012.0, 
        "x": 1999
      }, 
      {
        "y": 7494360.0, 
        "x": 2000
      }, 
      {
        "y": 7094792.0, 
        "x": 2001
      }, 
      {
        "y": 7143304.0, 
        "x": 2002
      }, 
      {
        "y": 7221005.0, 
        "x": 2003
      }, 
      {
        "y": 7271610.0, 
        "x": 2004
      }, 
      {
        "y": 7278513.0, 
        "x": 2005
      }, 
      {
        "y": 5984011.0, 
        "x": 2006
      }, 
      {
        "y": 5642210.0, 
        "x": 2007
      }, 
      {
        "y": 6593612.0, 
        "x": 2008
      }, 
      {
        "y": 7278013.0, 
        "x": 2009
      }, 
      {
        "y": 7370012.0, 
        "x": 2010
      }, 
      {
        "y": 7347413.0, 
        "x": 2011
      }
    ]
  ], 
  "Millet": [
    [
      {
        "y": 7395099.0, 
        "x": 1961
      }, 
      {
        "y": 6455697.0, 
        "x": 1962
      }, 
      {
        "y": 7505219.0, 
        "x": 1963
      }, 
      {
        "y": 7105204.0, 
        "x": 1964
      }, 
      {
        "y": 6565175.0, 
        "x": 1965
      }, 
      {
        "y": 7005745.0, 
        "x": 1966
      }, 
      {
        "y": 7005861.0, 
        "x": 1967
      }, 
      {
        "y": 6804953.0, 
        "x": 1968
      }, 
      {
        "y": 6904795.0, 
        "x": 1969
      }, 
      {
        "y": 6914718.0, 
        "x": 1970
      }, 
      {
        "y": 7004863.0, 
        "x": 1971
      }, 
      {
        "y": 6504728.0, 
        "x": 1972
      }, 
      {
        "y": 6003839.0, 
        "x": 1973
      }, 
      {
        "y": 6003786.0, 
        "x": 1974
      }, 
      {
        "y": 5303720.0, 
        "x": 1975
      }, 
      {
        "y": 4502868.0, 
        "x": 1976
      }, 
      {
        "y": 4482740.0, 
        "x": 1977
      }, 
      {
        "y": 4273766.0, 
        "x": 1978
      }, 
      {
        "y": 4175666.0, 
        "x": 1979
      }, 
      {
        "y": 3874318.0, 
        "x": 1980
      }, 
      {
        "y": 3892307.0, 
        "x": 1981
      }, 
      {
        "y": 4041035.0, 
        "x": 1982
      }, 
      {
        "y": 4088664.0, 
        "x": 1983
      }, 
      {
        "y": 3798356.0, 
        "x": 1984
      }, 
      {
        "y": 3318936.0, 
        "x": 1985
      }, 
      {
        "y": 2980886.0, 
        "x": 1986
      }, 
      {
        "y": 2688742.0, 
        "x": 1987
      }, 
      {
        "y": 2513604.0, 
        "x": 1988
      }, 
      {
        "y": 2397569.0, 
        "x": 1989
      }, 
      {
        "y": 2278860.0, 
        "x": 1990
      }, 
      {
        "y": 2081279.0, 
        "x": 1991
      }, 
      {
        "y": 1867722.0, 
        "x": 1992
      }, 
      {
        "y": 1832412.0, 
        "x": 1993
      }, 
      {
        "y": 1671845.0, 
        "x": 1994
      }, 
      {
        "y": 1522266.0, 
        "x": 1995
      }, 
      {
        "y": 1514361.0, 
        "x": 1996
      }, 
      {
        "y": 1442239.0, 
        "x": 1997
      }, 
      {
        "y": 1411406.0, 
        "x": 1998
      }, 
      {
        "y": 1329353.0, 
        "x": 1999
      }, 
      {
        "y": 1250296.0, 
        "x": 2000
      }, 
      {
        "y": 1148609.0, 
        "x": 2001
      }, 
      {
        "y": 1140098.0, 
        "x": 2002
      }, 
      {
        "y": 1024463.0, 
        "x": 2003
      }, 
      {
        "y": 916034.0, 
        "x": 2004
      }, 
      {
        "y": 849662.0, 
        "x": 2005
      }, 
      {
        "y": 858397.0, 
        "x": 2006
      }, 
      {
        "y": 839356.0, 
        "x": 2007
      }, 
      {
        "y": 815182.0, 
        "x": 2008
      }, 
      {
        "y": 788217.0, 
        "x": 2009
      }, 
      {
        "y": 755265.0, 
        "x": 2010
      }, 
      {
        "y": 745678.0, 
        "x": 2011
      }
    ]
  ], 
  "Rice, paddy": [
    [
      {
        "y": 27044821.0, 
        "x": 1961
      }, 
      {
        "y": 27711295.0, 
        "x": 1962
      }, 
      {
        "y": 28486877.0, 
        "x": 1963
      }, 
      {
        "y": 30348638.0, 
        "x": 1964
      }, 
      {
        "y": 30574538.0, 
        "x": 1965
      }, 
      {
        "y": 31294469.0, 
        "x": 1966
      }, 
      {
        "y": 31198309.0, 
        "x": 1967
      }, 
      {
        "y": 30662955.0, 
        "x": 1968
      }, 
      {
        "y": 31195067.0, 
        "x": 1969
      }, 
      {
        "y": 33107861.0, 
        "x": 1970
      }, 
      {
        "y": 35639653.0, 
        "x": 1971
      }, 
      {
        "y": 35851803.0, 
        "x": 1972
      }, 
      {
        "y": 35781144.0, 
        "x": 1973
      }, 
      {
        "y": 36254906.0, 
        "x": 1974
      }, 
      {
        "y": 36483975.0, 
        "x": 1975
      }, 
      {
        "y": 36969172.0, 
        "x": 1976
      }, 
      {
        "y": 36268342.0, 
        "x": 1977
      }, 
      {
        "y": 35173494.0, 
        "x": 1978
      }, 
      {
        "y": 34559678.0, 
        "x": 1979
      }, 
      {
        "y": 34482470.0, 
        "x": 1980
      }, 
      {
        "y": 33928102.0, 
        "x": 1981
      }, 
      {
        "y": 33697392.0, 
        "x": 1982
      }, 
      {
        "y": 33781788.0, 
        "x": 1983
      }, 
      {
        "y": 33765103.0, 
        "x": 1984
      }, 
      {
        "y": 32633684.0, 
        "x": 1985
      }, 
      {
        "y": 32797566.0, 
        "x": 1986
      }, 
      {
        "y": 32694296.0, 
        "x": 1987
      }, 
      {
        "y": 32458566.0, 
        "x": 1988
      }, 
      {
        "y": 33175855.0, 
        "x": 1989
      }, 
      {
        "y": 33518967.0, 
        "x": 1990
      }, 
      {
        "y": 33018802.0, 
        "x": 1991
      }, 
      {
        "y": 32487350.0, 
        "x": 1992
      }, 
      {
        "y": 30745927.0, 
        "x": 1993
      }, 
      {
        "y": 30537237.0, 
        "x": 1994
      }, 
      {
        "y": 31107479.0, 
        "x": 1995
      }, 
      {
        "y": 31753862.0, 
        "x": 1996
      }, 
      {
        "y": 32129200.0, 
        "x": 1997
      }, 
      {
        "y": 31571500.0, 
        "x": 1998
      }, 
      {
        "y": 31637100.0, 
        "x": 1999
      }, 
      {
        "y": 30301500.0, 
        "x": 2000
      }, 
      {
        "y": 29144019.0, 
        "x": 2001
      }, 
      {
        "y": 28508800.0, 
        "x": 2002
      }, 
      {
        "y": 26780124.0, 
        "x": 2003
      }, 
      {
        "y": 28615715.0, 
        "x": 2004
      }, 
      {
        "y": 29116400.0, 
        "x": 2005
      }, 
      {
        "y": 29557890.0, 
        "x": 2006
      }, 
      {
        "y": 29179116.0, 
        "x": 2007
      }, 
      {
        "y": 29493392.0, 
        "x": 2008
      }, 
      {
        "y": 29881590.0, 
        "x": 2009
      }, 
      {
        "y": 30117262.0, 
        "x": 2010
      }, 
      {
        "y": 30311300.0, 
        "x": 2011
      }
    ]
  ], 
  "Vegetables fresh nes": [
    [
      {
        "y": 1081594.0, 
        "x": 1961
      }, 
      {
        "y": 1186388.0, 
        "x": 1962
      }, 
      {
        "y": 993826.0, 
        "x": 1963
      }, 
      {
        "y": 881993.0, 
        "x": 1964
      }, 
      {
        "y": 933590.0, 
        "x": 1965
      }, 
      {
        "y": 903710.0, 
        "x": 1966
      }, 
      {
        "y": 905340.0, 
        "x": 1967
      }, 
      {
        "y": 886979.0, 
        "x": 1968
      }, 
      {
        "y": 859574.0, 
        "x": 1969
      }, 
      {
        "y": 725454.0, 
        "x": 1970
      }, 
      {
        "y": 795782.0, 
        "x": 1971
      }, 
      {
        "y": 754450.0, 
        "x": 1972
      }, 
      {
        "y": 833783.0, 
        "x": 1973
      }, 
      {
        "y": 824419.0, 
        "x": 1974
      }, 
      {
        "y": 846839.0, 
        "x": 1975
      }, 
      {
        "y": 838471.0, 
        "x": 1976
      }, 
      {
        "y": 881054.0, 
        "x": 1977
      }, 
      {
        "y": 1013952.0, 
        "x": 1978
      }, 
      {
        "y": 1006887.0, 
        "x": 1979
      }, 
      {
        "y": 937430.0, 
        "x": 1980
      }, 
      {
        "y": 1064652.0, 
        "x": 1981
      }, 
      {
        "y": 1263939.0, 
        "x": 1982
      }, 
      {
        "y": 1432539.0, 
        "x": 1983
      }, 
      {
        "y": 1642705.0, 
        "x": 1984
      }, 
      {
        "y": 1996800.0, 
        "x": 1985
      }, 
      {
        "y": 2488399.0, 
        "x": 1986
      }, 
      {
        "y": 2678547.0, 
        "x": 1987
      }, 
      {
        "y": 3079249.0, 
        "x": 1988
      }, 
      {
        "y": 3270217.0, 
        "x": 1989
      }, 
      {
        "y": 3198607.0, 
        "x": 1990
      }, 
      {
        "y": 3277800.0, 
        "x": 1991
      }, 
      {
        "y": 3495170.0, 
        "x": 1992
      }, 
      {
        "y": 4048780.0, 
        "x": 1993
      }, 
      {
        "y": 4372058.0, 
        "x": 1994
      }, 
      {
        "y": 4665220.0, 
        "x": 1995
      }, 
      {
        "y": 4803400.0, 
        "x": 1996
      }, 
      {
        "y": 5065608.0, 
        "x": 1997
      }, 
      {
        "y": 5365900.0, 
        "x": 1998
      }, 
      {
        "y": 6066500.0, 
        "x": 1999
      }, 
      {
        "y": 6724400.0, 
        "x": 2000
      }, 
      {
        "y": 7120600.0, 
        "x": 2001
      }, 
      {
        "y": 7371914.0, 
        "x": 2002
      }, 
      {
        "y": 7563912.0, 
        "x": 2003
      }, 
      {
        "y": 8064385.0, 
        "x": 2004
      }, 
      {
        "y": 8264716.0, 
        "x": 2005
      }, 
      {
        "y": 8361720.0, 
        "x": 2006
      }, 
      {
        "y": 8562315.0, 
        "x": 2007
      }, 
      {
        "y": 8663319.0, 
        "x": 2008
      }, 
      {
        "y": 9066275.0, 
        "x": 2009
      }, 
      {
        "y": 9365733.0, 
        "x": 2010
      }, 
      {
        "y": 9700307.0, 
        "x": 2011
      }
    ]
  ]
}